medutil/__init__.py
medutil/medutil.py
jjnsegutils-0.1.8.dist-info/LICENSE
jjnsegutils-0.1.8.dist-info/METADATA
jjnsegutils-0.1.8.dist-info/WHEEL
jjnsegutils-0.1.8.dist-info/top_level.txt
jjnsegutils-0.1.8.dist-info/RECORD
