Metadata-Version: 2.1
Name: jjnsegutils
Version: 0.1.8
Summary: A package of common utilities for medical images segmentation and evaluation.
Home-page: https://github.com/Ordgod/segutils
Author: Jingnan
Author-email: jiajingnan2222@gmail.com
License: UNKNOWN
Platform: UNKNOWN
Classifier: Programming Language :: Python :: 3
Classifier: License :: OSI Approved :: MIT License
Classifier: Operating System :: OS Independent
Requires-Python: >=3.6
License-File: LICENSE
Requires-Dist: pingouin
